.travis.yml
CHANGES.rst
CONTRIBUTORS.rst
MANIFEST.in
README.rst
bootstrap.py
buildout.cfg
setup.cfg
setup.py
travis.cfg
docs/LICENSE.GPL
docs/LICENSE.txt
src/collective/__init__.py
src/collective.lastmodified.egg-info/PKG-INFO
src/collective.lastmodified.egg-info/SOURCES.txt
src/collective.lastmodified.egg-info/dependency_links.txt
src/collective.lastmodified.egg-info/entry_points.txt
src/collective.lastmodified.egg-info/namespace_packages.txt
src/collective.lastmodified.egg-info/not-zip-safe
src/collective.lastmodified.egg-info/requires.txt
src/collective.lastmodified.egg-info/top_level.txt
src/collective/lastmodified/__init__.py
src/collective/lastmodified/configure.zcml
src/collective/lastmodified/extender.py
src/collective/lastmodified/i18n.py
src/collective/lastmodified/interfaces.py
src/collective/lastmodified/testing.py
src/collective/lastmodified/browser/__init__.py
src/collective/lastmodified/browser/configure.zcml
src/collective/lastmodified/browser/viewlets.py
src/collective/lastmodified/browser/templates/lastmodified.pt
src/collective/lastmodified/locales/collective.lastmodified.pot
src/collective/lastmodified/locales/en/LC_MESSAGES/collective.lastmodified.po
src/collective/lastmodified/locales/fr/LC_MESSAGES/collective.lastmodified.po
src/collective/lastmodified/locales/nl/LC_MESSAGES/collective.lastmodified.po
src/collective/lastmodified/profiles/default/browserlayer.xml
src/collective/lastmodified/profiles/default/metadata.xml
src/collective/lastmodified/tests/__init__.py
src/collective/lastmodified/tests/lastmodified.robot
src/collective/lastmodified/tests/test_extender.py
src/collective/lastmodified/tests/test_robot.py