Metadata-Version: 1.1
Name: collective.lastmodified
Version: 1.0
Summary: Adds a viewlet that displays the last modification date
Home-page: https://github.com/collective/
Author: Bram Pauwels
Author-email: brpauwels@cibg.irisnet.be
License: gpl
Platform: UNKNOWN
Classifier: Environment :: Web Environment
Classifier: Operating System :: OS Independent
Classifier: Framework :: Zope2
Classifier: Framework :: Plone
Classifier: Framework :: Plone :: 4.2
Classifier: Framework :: Plone :: 4.3
Classifier: Programming Language :: Python
Classifier: Programming Language :: Python :: 2.6
Classifier: Programming Language :: Python :: 2.7
Classifier: Topic :: Software Development :: Libraries :: Python Modules
